README.rst
README.txt
setup.cfg
setup.py
wikipedia_parser/__init__.py
wikipedia_parser.egg-info/PKG-INFO
wikipedia_parser.egg-info/SOURCES.txt
wikipedia_parser.egg-info/dependency_links.txt
wikipedia_parser.egg-info/not-zip-safe
wikipedia_parser.egg-info/pbr.json
wikipedia_parser.egg-info/requires.txt
wikipedia_parser.egg-info/top_level.txt
wikipedia_parser/infobox/Infobox.py
wikipedia_parser/infobox/__init__.py
wikipedia_parser/infobox/clean_text.py
wikipedia_parser/infobox/image_helpers.py
wikipedia_parser/infobox/names.py
wikipedia_parser/infobox/wikitext_helpers.py
wikipedia_parser/infobox/wikitext_parser.py
wikipedia_parser/tests/__init__.py
wikipedia_parser/tests/test_Infobox.py
wikipedia_parser/tests/test_WikipediaAPI.py
wikipedia_parser/third_party_adapters/__init__.py
wikipedia_parser/third_party_adapters/api_adapters.py
wikipedia_parser/third_party_adapters/parserfromhell_adapter.py
wikipedia_parser/tools/__init__.py
wikipedia_parser/tools/common.py
wikipedia_parser/tools/dict_helpers.py
wikipedia_parser/wikipedia_api/WikipediaAPI.py
wikipedia_parser/wikipedia_api/__init__.py
wikipedia_parser/wikipedia_api/http_calls.py
wikipedia_parser/wikipedia_api/json_parsers.py
wikipedia_parser/wikipedia_api/urls.py