Metadata-Version: 1.1
Name: wikipedia-parser
Version: 0.1.2
Summary: Fetches wikipedia api resources and parses into data structures
Home-page: https://github.com/ojones/wikipedia_parser
Author: Oswald Jones
Author-email: wakeupoj@gmail.com
License: MIT
Download-URL: https://github.com/ojones/wikipedia_parser/tarball/0.1
Platform: UNKNOWN
